odoo/addons/coupon_incompatibility/README.rst
odoo/addons/coupon_incompatibility/__init__.py
odoo/addons/coupon_incompatibility/__manifest__.py
odoo/addons/coupon_incompatibility/i18n/coupon_incompatibility.pot
odoo/addons/coupon_incompatibility/i18n/es.po
odoo/addons/coupon_incompatibility/models/__init__.py
odoo/addons/coupon_incompatibility/models/coupon_program.py
odoo/addons/coupon_incompatibility/readme/CONFIGURE.rst
odoo/addons/coupon_incompatibility/readme/CONTRIBUTORS.rst
odoo/addons/coupon_incompatibility/readme/DESCRIPTION.rst
odoo/addons/coupon_incompatibility/static/description/icon.png
odoo/addons/coupon_incompatibility/static/description/icon.svg
odoo/addons/coupon_incompatibility/static/description/index.html
odoo/addons/coupon_incompatibility/tests/__init__.py
odoo/addons/coupon_incompatibility/tests/test_coupon_incompatibility.py
odoo/addons/coupon_incompatibility/views/sale_coupon_program_views.xml
odoo_addon_coupon_incompatibility-15.0.1.0.0.5.dist-info/METADATA
odoo_addon_coupon_incompatibility-15.0.1.0.0.5.dist-info/WHEEL
odoo_addon_coupon_incompatibility-15.0.1.0.0.5.dist-info/top_level.txt
odoo_addon_coupon_incompatibility-15.0.1.0.0.5.dist-info/RECORD
